setup.py
flowz/__init__.py
flowz/app.py
flowz/artifacts.py
flowz/compat.py
flowz/util.py
flowz.egg-info/PKG-INFO
flowz.egg-info/SOURCES.txt
flowz.egg-info/dependency_links.txt
flowz.egg-info/requires.txt
flowz.egg-info/top_level.txt
flowz/channels/__init__.py
flowz/channels/core.py
flowz/channels/management.py
flowz/channels/tools.py
flowz/examples/__init__.py
flowz/examples/nested_channel_handling.py
flowz/examples/syntax.py
flowz/test/__init__.py
flowz/test/application_test.py
flowz/test/manager_test.py
flowz/test/artifacts/__init__.py
flowz/test/artifacts/artifacts_test.py
flowz/test/artifacts/exception_logging_test.py
flowz/test/channels/__init__.py
flowz/test/channels/helpers_test.py
flowz/test/channels/iteration_test.py
flowz/test/channels/read_bound_test.py
flowz/test/channels/tools_test.py
flowz/test/channels/util.py
flowz/test/util/__init__.py
flowz/test/util/assembly_test.py
flowz/test/util/last_result_test.py
flowz/test/util/min_max_test.py