Metadata-Version: 1.0
Name: flowz
Version: 1.1.0
Summary: Async I/O - oriented dependency programming framework
Home-page: https://github.com/ethanrowe/flowz
Author: Ethan Rowe
Author-email: ethan@the-rowes.com
License: MIT
Platform: UNKNOWN
